LICENSE
MANIFEST.in
README.rst
requirements.txt
setup.py
discoverpy/__init__.py
discoverpy/application.py
discoverpy/endpoint.py
discoverpy/links.py
discoverpy/query.py
discoverpy/request.py
discoverpy/service.py
discoverpy/validator.py
discoverpy.egg-info/PKG-INFO
discoverpy.egg-info/SOURCES.txt
discoverpy.egg-info/dependency_links.txt
discoverpy.egg-info/entry_points.txt
discoverpy.egg-info/requires.txt
discoverpy.egg-info/top_level.txt
discoverpy/client/__init__.py
discoverpy/client/api.py
discoverpy/client/http.py
discoverpy/client/resource.py
discoverpy/discover/__init__.py
discoverpy/discover/models.py
discoverpy/discover/service.py
discoverpy/resources/__init__.py
discoverpy/resources/base.py
discoverpy/resources/exceptions.py
discoverpy/resources/readonly.py
discoverpy/resources/sqlalchemy.py