Metadata-Version: 1.0
Name: discoverpy
Version: 0.3.1
Summary: REST framework for discoverable services.
Home-page: https://github.com/kevinconway/discover.py
Author: Kevin Conway
Author-email: kevinjacobconway@gmail.com
License: MIT
Platform: UNKNOWN
